cvxrisk/__init__.py
cvxrisk/bounds.py
cvxrisk/model.py
cvxrisk/cvar/__init__.py
cvxrisk/cvar/cvar.py
cvxrisk/factor/__init__.py
cvxrisk/factor/factor.py
cvxrisk/linalg/__init__.py
cvxrisk/linalg/cholesky.py
cvxrisk/linalg/pca.py
cvxrisk/linalg/valid.py
cvxrisk/portfolio/__init__.py
cvxrisk/portfolio/min_risk.py
cvxrisk/random/__init__.py
cvxrisk/random/rand_cov.py
cvxrisk/sample/__init__.py
cvxrisk/sample/sample.py
cvxrisk-1.4.11.dist-info/METADATA
cvxrisk-1.4.11.dist-info/WHEEL
cvxrisk-1.4.11.dist-info/licenses/LICENSE
cvxrisk-1.4.11.dist-info/RECORD
