Metadata-Version: 2.4
Name: cvxrisk
Version: 1.4.11
Summary: Simple riskengine for cvxpy
Project-URL: repository, https://github.com/cvxgrp/cvxrisk
Author-email: Thomas Schmelzer <thomas.schmelzer@gmail.com>
License-File: LICENSE
Requires-Python: >=3.12
Requires-Dist: cvxpy-base>=1.5.0
Requires-Dist: numpy>=2.0
Requires-Dist: pandas>=2.2.3
Requires-Dist: scikit-learn>=1.6.1
Requires-Dist: scipy>=1.14.1
Provides-Extra: clarabel
Requires-Dist: clarabel>=0.9.0; extra == 'clarabel'
Provides-Extra: dev
Requires-Dist: cvxsimulator>=1.4.0; extra == 'dev'
Requires-Dist: marimo>=0.13.15; extra == 'dev'
Requires-Dist: micropip>=0.9.0; extra == 'dev'
Requires-Dist: polars>=1.24.0; extra == 'dev'
Requires-Dist: pre-commit>=4.0.1; extra == 'dev'
Requires-Dist: pytest-cov>=6.0.0; extra == 'dev'
Requires-Dist: pytest>=8.3.3; extra == 'dev'
Provides-Extra: mosek
Requires-Dist: mosek>=11.0; extra == 'mosek'
